{
  "configurations": [
    {
      "name": "x64-Release",
      "generator": "Ninja",
      "configurationType": "Release",
      "buildRoot": "${projectDir}\\out\\build\\${name}",
      "installRoot": "${projectDir}\\out\\install\\${name}",
      "cmakeCommandArgs": "-DWX_WIDGETS_DIR=D:\\3_thiredpaty\\wxWidgets\\wxWidgets-3.1.2",
      "buildCommandArgs": "-v",
      "ctestCommandArgs": "",
      "inheritEnvironments": [ "msvc_x64_x64" ],
      "variables": []
    },
    {
      "name": "x86-Release",
      "generator": "Ninja",
      "configurationType": "Release",
      "buildRoot": "${projectDir}\\out\\build\\${name}",
      "installRoot": "${projectDir}\\out\\install\\${name}",
      "cmakeCommandArgs": "-DWX_WIDGETS_DIR=D:\\3_thiredpaty\\wxWidgets\\wxWidgets-3.1.2",
      "buildCommandArgs": "-v",
      "ctestCommandArgs": "",
      "inheritEnvironments": [ "msvc_x86" ],
      "variables": []
    }
  ]
}